{
  "gitSyncId": "686cd638814b5b2eb4bb0f19_8f933047-e123-4b8b-a90e-b2518d327aa3",
  "id": "Page1_getPageContent",
  "pluginId": "postgres-plugin",
  "pluginType": "DB",
  "unpublishedAction": {
    "actionConfiguration": {
      "body": "SELECT page_content FROM api_listingdata WHERE unique_identifier={{skuDropdown.selectedOptionValue}};",
      "encodeParamsToggle": true,
      "paginationType": "NONE",
      "pluginSpecifiedTemplates": [
        {
          "value": true
        }
      ],
      "timeoutInMillisecond": 10000
    },
    "confirmBeforeExecute": false,
    "datasource": {
      "id": "Datavio datasource 1",
      "isAutoGenerated": false,
      "name": "Datavio datasource 1",
      "pluginId": "postgres-plugin"
    },
    "dynamicBindingPathList": [
      {
        "key": "body"
      }
    ],
    "name": "getPageContent",
    "pageId": "Page1",
    "runBehaviour": "ON_PAGE_LOAD",
    "userSetOnLoad": true
  }
}